{"_format":"","paths":{"artifacts":"out","build_infos":"out/build-info","sources":"src/PositionLedgerV4.sol","tests":"test","scripts":"script","libraries":["lib"]},"files":{"src/RouterV6.sol":{"lastModificationDate":1770412956284,"contentHash":"03843138585e9f77","interfaceReprHash":null,"sourceName":"src/RouterV6.sol","imports":["src/interfaces/IERC20.sol"],"versionRequirement":"^0.8.20","artifacts":{"ILPPool":{"0.8.20":{"default":{"path":"RouterV6.sol/ILPPool.json","build_id":"e3f0371955acae8e"}}},"IPositionLedgerV4":{"0.8.20":{"default":{"path":"RouterV6.sol/IPositionLedgerV4.json","build_id":"e3f0371955acae8e"}}},"RouterV6":{"0.8.20":{"default":{"path":"RouterV6.sol/RouterV6.json","build_id":"e3f0371955acae8e"}}}},"seenByCompiler":true},"src/interfaces/IERC20.sol":{"lastModificationDate":1770357176209,"contentHash":"dee60d99d22ea073","interfaceReprHash":null,"sourceName":"src/interfaces/IERC20.sol","imports":[],"versionRequirement":"^0.8.20","artifacts":{"IERC20":{"0.8.20":{"default":{"path":"IERC20.sol/IERC20.json","build_id":"e3f0371955acae8e"}}}},"seenByCompiler":true}},"builds":["e3f0371955acae8e"],"profiles":{"default":{"solc":{"optimizer":{"enabled":true,"runs":200},"metadata":{"useLiteralContent":false,"bytecodeHash":"ipfs","appendCBOR":true},"outputSelection":{"*":{"*":["abi","evm.bytecode.object","evm.bytecode.sourceMap","evm.bytecode.linkReferences","evm.deployedBytecode.object","evm.deployedBytecode.sourceMap","evm.deployedBytecode.linkReferences","evm.deployedBytecode.immutableReferences","evm.methodIdentifiers","metadata"]}},"evmVersion":"shanghai","viaIR":true,"libraries":{}},"vyper":{"evmVersion":"shanghai","outputSelection":{"*":{"*":["abi","evm.bytecode","evm.deployedBytecode"]}}}}},"preprocessed":false,"mocks":[]}